nodestream_plugin_meta/__init__.py
nodestream_plugin_meta/plugin.py
nodestream_plugin_meta-0.14.0.dist-info/LICENSE
nodestream_plugin_meta-0.14.0.dist-info/METADATA
nodestream_plugin_meta-0.14.0.dist-info/WHEEL
nodestream_plugin_meta-0.14.0.dist-info/entry_points.txt
nodestream_plugin_meta-0.14.0.dist-info/RECORD
